{"v":4,"entries":{"autocomplete--default":{"type":"story","id":"autocomplete--default","name":"Default","title":"Autocomplete","importPath":"./src/lib/components/ui/atoms/Autocomplete.stories.tsx","tags":["story"]},"basictoast--error":{"type":"story","id":"basictoast--error","name":"Error","title":"BasicToast","importPath":"./src/lib/components/ui/atoms/BasicToast.stories.tsx","tags":["story"]},"basictoast--success":{"type":"story","id":"basictoast--success","name":"Success","title":"BasicToast","importPath":"./src/lib/components/ui/atoms/BasicToast.stories.tsx","tags":["story"]},"basictoast--alert":{"type":"story","id":"basictoast--alert","name":"Alert","title":"BasicToast","importPath":"./src/lib/components/ui/atoms/BasicToast.stories.tsx","tags":["story"]},"button--primary":{"type":"story","id":"button--primary","name":"Primary","title":"Button","importPath":"./src/lib/components/ui/atoms/Button.stories.tsx","tags":["story"]},"button--custom-styles":{"type":"story","id":"button--custom-styles","name":"Custom Styles","title":"Button","importPath":"./src/lib/components/ui/atoms/Button.stories.tsx","tags":["story"]},"buttoncardmain--default":{"type":"story","id":"buttoncardmain--default","name":"Default","title":"ButtonCardMain","importPath":"./src/lib/components/ui/atoms/ButtonCardMain.stories.tsx","tags":["story"]},"buttoncardmain--custom-styles":{"type":"story","id":"buttoncardmain--custom-styles","name":"Custom Styles","title":"ButtonCardMain","importPath":"./src/lib/components/ui/atoms/ButtonCardMain.stories.tsx","tags":["story"]},"buttoncardsecondary--default":{"type":"story","id":"buttoncardsecondary--default","name":"Default","title":"ButtonCardSecondary","importPath":"./src/lib/components/ui/atoms/ButtonCardSecondary.stories.tsx","tags":["story"]},"buttoncardsecondary--custom-styles":{"type":"story","id":"buttoncardsecondary--custom-styles","name":"Custom Styles","title":"ButtonCardSecondary","importPath":"./src/lib/components/ui/atoms/ButtonCardSecondary.stories.tsx","tags":["story"]},"buttondanger--default":{"type":"story","id":"buttondanger--default","name":"Default","title":"ButtonDanger","importPath":"./src/lib/components/ui/atoms/ButtonDanger.stories.tsx","tags":["story"]},"buttondanger--custom-styles":{"type":"story","id":"buttondanger--custom-styles","name":"Custom Styles","title":"ButtonDanger","importPath":"./src/lib/components/ui/atoms/ButtonDanger.stories.tsx","tags":["story"]},"buttonmain--default":{"type":"story","id":"buttonmain--default","name":"Default","title":"ButtonMain","importPath":"./src/lib/components/ui/atoms/ButtonMain.stories.tsx","tags":["story"]},"buttonmain--custom-styles":{"type":"story","id":"buttonmain--custom-styles","name":"Custom Styles","title":"ButtonMain","importPath":"./src/lib/components/ui/atoms/ButtonMain.stories.tsx","tags":["story"]},"buttonsecondary--default":{"type":"story","id":"buttonsecondary--default","name":"Default","title":"ButtonSecondary","importPath":"./src/lib/components/ui/atoms/ButtonSecondary.stories.tsx","tags":["story"]},"buttonsecondary--custom-styles":{"type":"story","id":"buttonsecondary--custom-styles","name":"Custom Styles","title":"ButtonSecondary","importPath":"./src/lib/components/ui/atoms/ButtonSecondary.stories.tsx","tags":["story"]},"bottomtext--default":{"type":"story","id":"bottomtext--default","name":"Default","title":"BottomText","importPath":"./src/lib/components/ui/atoms/ButtonText.stories.tsx","tags":["story"]},"buttonsgroup--default":{"type":"story","id":"buttonsgroup--default","name":"Default","title":"ButtonsGroup","importPath":"./src/lib/components/ui/atoms/ButtonsGroup.stories.tsx","tags":["story"]},"canvatesttwo--default":{"type":"story","id":"canvatesttwo--default","name":"Default","title":"CanvaTestTwo","importPath":"./src/lib/components/ui/atoms/CanvaTestTwo.stories.tsx","tags":["story"]},"card--default":{"type":"story","id":"card--default","name":"Default","title":"Card","importPath":"./src/lib/components/ui/atoms/Card.stories.tsx","tags":["story"]},"card--clickable-card":{"type":"story","id":"card--clickable-card","name":"Clickable Card","title":"Card","importPath":"./src/lib/components/ui/atoms/Card.stories.tsx","tags":["story"]},"coverbackground--default":{"type":"story","id":"coverbackground--default","name":"Default","title":"CoverBackground","importPath":"./src/lib/components/ui/atoms/CoverBackground.stories.tsx","tags":["story"]},"coverbackground--with-link":{"type":"story","id":"coverbackground--with-link","name":"With Link","title":"CoverBackground","importPath":"./src/lib/components/ui/atoms/CoverBackground.stories.tsx","tags":["story"]},"formtitle--default":{"type":"story","id":"formtitle--default","name":"Default","title":"FormTitle","importPath":"./src/lib/components/ui/atoms/FormTitle.stories.tsx","tags":["story"]},"googlebutton--default":{"type":"story","id":"googlebutton--default","name":"Default","title":"GoogleButton","importPath":"./src/lib/components/ui/atoms/GoogleButton.stories.tsx","tags":["story"]},"header--default":{"type":"story","id":"header--default","name":"Default","title":"Header","importPath":"./src/lib/components/ui/atoms/Headers.stories.tsx","tags":["story"]},"helpmenu--default":{"type":"story","id":"helpmenu--default","name":"Default","title":"HelpMenu","importPath":"./src/lib/components/ui/atoms/HelpMenu.stories.tsx","tags":["story"]},"input--text":{"type":"story","id":"input--text","name":"Text","title":"Input","importPath":"./src/lib/components/ui/atoms/Input.stories.tsx","tags":["story"]},"input--password":{"type":"story","id":"input--password","name":"Password","title":"Input","importPath":"./src/lib/components/ui/atoms/Input.stories.tsx","tags":["story"]},"input--email":{"type":"story","id":"input--email","name":"Email","title":"Input","importPath":"./src/lib/components/ui/atoms/Input.stories.tsx","tags":["story"]},"input--number":{"type":"story","id":"input--number","name":"Number","title":"Input","importPath":"./src/lib/components/ui/atoms/Input.stories.tsx","tags":["story"]},"input--search":{"type":"story","id":"input--search","name":"Search","title":"Input","importPath":"./src/lib/components/ui/atoms/Input.stories.tsx","tags":["story"]},"input--custom-style":{"type":"story","id":"input--custom-style","name":"Custom Style","title":"Input","importPath":"./src/lib/components/ui/atoms/Input.stories.tsx","tags":["story"]},"input--required":{"type":"story","id":"input--required","name":"Required","title":"Input","importPath":"./src/lib/components/ui/atoms/Input.stories.tsx","tags":["story"]},"inputcolor--default":{"type":"story","id":"inputcolor--default","name":"Default","title":"InputColor","importPath":"./src/lib/components/ui/atoms/InputColor.stories.tsx","tags":["story"]},"inputcolor--with-error":{"type":"story","id":"inputcolor--with-error","name":"With Error","title":"InputColor","importPath":"./src/lib/components/ui/atoms/InputColor.stories.tsx","tags":["story"]},"inputcolor--custom-on-change":{"type":"story","id":"inputcolor--custom-on-change","name":"Custom On Change","title":"InputColor","importPath":"./src/lib/components/ui/atoms/InputColor.stories.tsx","tags":["story"]},"nodatainfo--default":{"type":"story","id":"nodatainfo--default","name":"Default","title":"NoDataInfo","importPath":"./src/lib/components/ui/atoms/NoDataInfo.stories.tsx","tags":["story"]},"nodatainfo--with-hover-text":{"type":"story","id":"nodatainfo--with-hover-text","name":"With Hover Text","title":"NoDataInfo","importPath":"./src/lib/components/ui/atoms/NoDataInfo.stories.tsx","tags":["story"]},"pagetitle--default":{"type":"story","id":"pagetitle--default","name":"Default","title":"PageTitle","importPath":"./src/lib/components/ui/atoms/PageTitle.stories.tsx","tags":["story"]},"pagetitle--with-back-button":{"type":"story","id":"pagetitle--with-back-button","name":"With Back Button","title":"PageTitle","importPath":"./src/lib/components/ui/atoms/PageTitle.stories.tsx","tags":["story"]},"pagetitle--custom-styling":{"type":"story","id":"pagetitle--custom-styling","name":"Custom Styling","title":"PageTitle","importPath":"./src/lib/components/ui/atoms/PageTitle.stories.tsx","tags":["story"]},"pagination--default":{"type":"story","id":"pagination--default","name":"Default","title":"Pagination","importPath":"./src/lib/components/ui/atoms/Pagination.stories.tsx","tags":["story"]},"pagination--with-rows-per-page":{"type":"story","id":"pagination--with-rows-per-page","name":"With Rows Per Page","title":"Pagination","importPath":"./src/lib/components/ui/atoms/Pagination.stories.tsx","tags":["story"]},"pagination--with-custom-pagination":{"type":"story","id":"pagination--with-custom-pagination","name":"With Custom Pagination","title":"Pagination","importPath":"./src/lib/components/ui/atoms/Pagination.stories.tsx","tags":["story"]},"popoverboards--default":{"type":"story","id":"popoverboards--default","name":"Default","title":"PopoverBoards","importPath":"./src/lib/components/ui/atoms/PopoverBoards.stories.tsx","tags":["story"]},"popovermenu--default":{"type":"story","id":"popovermenu--default","name":"Default","title":"PopoverMenu","importPath":"./src/lib/components/ui/atoms/PopoverMenu.stories.tsx","tags":["story"]},"popovertrellolist--default":{"type":"story","id":"popovertrellolist--default","name":"Default","title":"PopoverTrelloList","importPath":"./src/lib/components/ui/atoms/PopoverTrelloList.stories.tsx","tags":["story"]},"remindersmenu--default":{"type":"story","id":"remindersmenu--default","name":"Default","title":"RemindersMenu","importPath":"./src/lib/components/ui/atoms/RemindersMenu.stories.tsx","tags":["story"]},"select--default":{"type":"story","id":"select--default","name":"Default","title":"Select","importPath":"./src/lib/components/ui/atoms/Select.stories.tsx","tags":["story"]},"spinner--default":{"type":"story","id":"spinner--default","name":"Default","title":"Spinner","importPath":"./src/lib/components/ui/atoms/Spinner.stories.tsx","tags":["story"]},"switch--default":{"type":"story","id":"switch--default","name":"Default","title":"Switch","importPath":"./src/lib/components/ui/atoms/Switch.stories.tsx","tags":["story"]},"switch--disabled":{"type":"story","id":"switch--disabled","name":"Disabled","title":"Switch","importPath":"./src/lib/components/ui/atoms/Switch.stories.tsx","tags":["story"]},"switch--with-error":{"type":"story","id":"switch--with-error","name":"With Error","title":"Switch","importPath":"./src/lib/components/ui/atoms/Switch.stories.tsx","tags":["story"]},"taglist--default":{"type":"story","id":"taglist--default","name":"Default","title":"TagList","importPath":"./src/lib/components/ui/atoms/TagList.stories.tsx","tags":["story"]},"taglist--empty-state":{"type":"story","id":"taglist--empty-state","name":"Empty State","title":"TagList","importPath":"./src/lib/components/ui/atoms/TagList.stories.tsx","tags":["story"]},"taglistdots--default":{"type":"story","id":"taglistdots--default","name":"Default","title":"TagListDots","importPath":"./src/lib/components/ui/atoms/TagListDots.stories.tsx","tags":["story"]},"taglistdots--empty-state":{"type":"story","id":"taglistdots--empty-state","name":"Empty State","title":"TagListDots","importPath":"./src/lib/components/ui/atoms/TagListDots.stories.tsx","tags":["story"]},"tagsselector--default":{"type":"story","id":"tagsselector--default","name":"Default","title":"TagsSelector","importPath":"./src/lib/components/ui/atoms/TagsSelector.stories.tsx","tags":["story"]},"textarea--default":{"type":"story","id":"textarea--default","name":"Default","title":"TextArea","importPath":"./src/lib/components/ui/atoms/TextArea.stories.tsx","tags":["story"]},"tooltip--info-tooltip":{"type":"story","id":"tooltip--info-tooltip","name":"Info Tooltip","title":"Tooltip","importPath":"./src/lib/components/ui/atoms/Tooltip.stories.tsx","tags":["story"]},"tooltip--augmented-tooltip":{"type":"story","id":"tooltip--augmented-tooltip","name":"Augmented Tooltip","title":"Tooltip","importPath":"./src/lib/components/ui/atoms/Tooltip.stories.tsx","tags":["story"]},"tooltip--custom-tooltip":{"type":"story","id":"tooltip--custom-tooltip","name":"Custom Tooltip","title":"Tooltip","importPath":"./src/lib/components/ui/atoms/Tooltip.stories.tsx","tags":["story"]},"barchart--grouped-bar-chart":{"type":"story","id":"barchart--grouped-bar-chart","name":"Grouped Bar Chart","title":"BarChart","importPath":"./src/lib/components/ui/atoms/charts/BarChart.stories.tsx","tags":["story"]},"barchart--stacked-bar-chart":{"type":"story","id":"barchart--stacked-bar-chart","name":"Stacked Bar Chart","title":"BarChart","importPath":"./src/lib/components/ui/atoms/charts/BarChart.stories.tsx","tags":["story"]},"barchart--rotated-bar-chart":{"type":"story","id":"barchart--rotated-bar-chart","name":"Rotated Bar Chart","title":"BarChart","importPath":"./src/lib/components/ui/atoms/charts/BarChart.stories.tsx","tags":["story"]},"circularchart--basic-circular-chart":{"type":"story","id":"circularchart--basic-circular-chart","name":"Basic Circular Chart","title":"CircularChart","importPath":"./src/lib/components/ui/atoms/charts/CircularChart.stories.tsx","tags":["story"]},"funnelchart--basic-funnel-chart":{"type":"story","id":"funnelchart--basic-funnel-chart","name":"Basic Funnel Chart","title":"FunnelChart","importPath":"./src/lib/components/ui/atoms/charts/FunnelChart.stories.tsx","tags":["story"]},"geochart--basic-geo-chart":{"type":"story","id":"geochart--basic-geo-chart","name":"Basic Geo Chart","title":"GeoChart","importPath":"./src/lib/components/ui/atoms/charts/GeoChart.stories.tsx","tags":["story"]},"linechart--basic-line-chart":{"type":"story","id":"linechart--basic-line-chart","name":"Basic Line Chart","title":"LineChart","importPath":"./src/lib/components/ui/atoms/charts/LineChart.stories.tsx","tags":["story"]},"piechart--basic-pie-chart":{"type":"story","id":"piechart--basic-pie-chart","name":"Basic Pie Chart","title":"PieChart","importPath":"./src/lib/components/ui/atoms/charts/PieChart.stories.tsx","tags":["story"]},"piechart--pie-chart-without-legend":{"type":"story","id":"piechart--pie-chart-without-legend","name":"Pie Chart Without Legend","title":"PieChart","importPath":"./src/lib/components/ui/atoms/charts/PieChart.stories.tsx","tags":["story"]},"piechart--pie-chart-without-link-labels":{"type":"story","id":"piechart--pie-chart-without-link-labels","name":"Pie Chart Without Link Labels","title":"PieChart","importPath":"./src/lib/components/ui/atoms/charts/PieChart.stories.tsx","tags":["story"]},"piechart--custom-styled-pie-chart":{"type":"story","id":"piechart--custom-styled-pie-chart","name":"Custom Styled Pie Chart","title":"PieChart","importPath":"./src/lib/components/ui/atoms/charts/PieChart.stories.tsx","tags":["story"]},"radarchart--basic-radar-chart":{"type":"story","id":"radarchart--basic-radar-chart","name":"Basic Radar Chart","title":"RadarChart","importPath":"./src/lib/components/ui/atoms/charts/RadarChart.stories.tsx","tags":["story"]},"radarchart--radar-chart-without-legend":{"type":"story","id":"radarchart--radar-chart-without-legend","name":"Radar Chart Without Legend","title":"RadarChart","importPath":"./src/lib/components/ui/atoms/charts/RadarChart.stories.tsx","tags":["story"]},"inputfile--single-file-input":{"type":"story","id":"inputfile--single-file-input","name":"Single File Input","title":"InputFile","importPath":"./src/lib/components/ui/atoms/input-files/InputFile.stories.tsx","tags":["story"]},"inputfile--multiple-file-input":{"type":"story","id":"inputfile--multiple-file-input","name":"Multiple File Input","title":"InputFile","importPath":"./src/lib/components/ui/atoms/input-files/InputFile.stories.tsx","tags":["story"]},"inputfile--file-with-error":{"type":"story","id":"inputfile--file-with-error","name":"File With Error","title":"InputFile","importPath":"./src/lib/components/ui/atoms/input-files/InputFile.stories.tsx","tags":["story"]},"userecorder--basic-use-recorder":{"type":"story","id":"userecorder--basic-use-recorder","name":"Basic Use Recorder","title":"useRecorder","importPath":"./src/lib/components/ui/atoms/useRecorder.stories.tsx","tags":["story"]},"alert--info-alert":{"type":"story","id":"alert--info-alert","name":"Info Alert","title":"Alert","importPath":"./src/lib/components/ui/molecules/Alert.stories.tsx","tags":["story"]},"alert--warning-alert":{"type":"story","id":"alert--warning-alert","name":"Warning Alert","title":"Alert","importPath":"./src/lib/components/ui/molecules/Alert.stories.tsx","tags":["story"]},"alert--error-alert":{"type":"story","id":"alert--error-alert","name":"Error Alert","title":"Alert","importPath":"./src/lib/components/ui/molecules/Alert.stories.tsx","tags":["story"]},"basiccardnotes--text-note":{"type":"story","id":"basiccardnotes--text-note","name":"Text Note","title":"BasicCardNotes","importPath":"./src/lib/components/ui/molecules/BasicCardNotes.stories.tsx","tags":["story"]},"basiccardnotes--audio-note":{"type":"story","id":"basiccardnotes--audio-note","name":"Audio Note","title":"BasicCardNotes","importPath":"./src/lib/components/ui/molecules/BasicCardNotes.stories.tsx","tags":["story"]},"basiccardnotes--draw-note":{"type":"story","id":"basiccardnotes--draw-note","name":"Draw Note","title":"BasicCardNotes","importPath":"./src/lib/components/ui/molecules/BasicCardNotes.stories.tsx","tags":["story"]},"checkbox--basic-checkbox":{"type":"story","id":"checkbox--basic-checkbox","name":"Basic Checkbox","title":"Checkbox","importPath":"./src/lib/components/ui/molecules/Checkbox.stories.tsx","tags":["story"]},"checkbox--checked-checkbox":{"type":"story","id":"checkbox--checked-checkbox","name":"Checked Checkbox","title":"Checkbox","importPath":"./src/lib/components/ui/molecules/Checkbox.stories.tsx","tags":["story"]},"checkbox--disabled-checkbox":{"type":"story","id":"checkbox--disabled-checkbox","name":"Disabled Checkbox","title":"Checkbox","importPath":"./src/lib/components/ui/molecules/Checkbox.stories.tsx","tags":["story"]},"checkbox--checkbox-with-error":{"type":"story","id":"checkbox--checkbox-with-error","name":"Checkbox With Error","title":"Checkbox","importPath":"./src/lib/components/ui/molecules/Checkbox.stories.tsx","tags":["story"]},"modal--basic-modal":{"type":"story","id":"modal--basic-modal","name":"Basic Modal","title":"Modal","importPath":"./src/lib/components/ui/molecules/Modal.stories.tsx","tags":["story"]},"modal--modal-with-close-button":{"type":"story","id":"modal--modal-with-close-button","name":"Modal With Close Button","title":"Modal","importPath":"./src/lib/components/ui/molecules/Modal.stories.tsx","tags":["story"]},"modalswal--basic-modal-swal":{"type":"story","id":"modalswal--basic-modal-swal","name":"Basic Modal Swal","title":"ModalSwal","importPath":"./src/lib/components/ui/molecules/ModalSwal.stories.tsx","tags":["story"]},"sectionheader--basic-section-header":{"type":"story","id":"sectionheader--basic-section-header","name":"Basic Section Header","title":"SectionHeader","importPath":"./src/lib/components/ui/molecules/SectionHeader.stories.tsx","tags":["story"]},"sectionheader--section-header-with-actions":{"type":"story","id":"sectionheader--section-header-with-actions","name":"Section Header With Actions","title":"SectionHeader","importPath":"./src/lib/components/ui/molecules/SectionHeader.stories.tsx","tags":["story"]},"sectionheader--section-header-with-long-titles":{"type":"story","id":"sectionheader--section-header-with-long-titles","name":"Section Header With Long Titles","title":"SectionHeader","importPath":"./src/lib/components/ui/molecules/SectionHeader.stories.tsx","tags":["story"]},"teammatecard--basic-teammate-card":{"type":"story","id":"teammatecard--basic-teammate-card","name":"Basic Teammate Card","title":"TeammateCard","importPath":"./src/lib/components/ui/molecules/TeammateCard.stories.tsx","tags":["story"]},"teammatecard--teammate-card-without-image":{"type":"story","id":"teammatecard--teammate-card-without-image","name":"Teammate Card Without Image","title":"TeammateCard","importPath":"./src/lib/components/ui/molecules/TeammateCard.stories.tsx","tags":["story"]},"datagrid--basic-data-grid":{"type":"story","id":"datagrid--basic-data-grid","name":"Basic Data Grid","title":"DataGrid","importPath":"./src/lib/components/ui/objects/DataGrid.stories.tsx","tags":["story"]},"menu--default-menu":{"type":"story","id":"menu--default-menu","name":"Default Menu","title":"Menu","importPath":"./src/lib/components/ui/objects/Menu.stories.tsx","tags":["story"]},"notescontainer--default-notes-container":{"type":"story","id":"notescontainer--default-notes-container","name":"Default Notes Container","title":"NotesContainer","importPath":"./src/lib/components/ui/objects/NotesContainer.stories.tsx","tags":["story"]},"richeditor--default-rich-editor":{"type":"story","id":"richeditor--default-rich-editor","name":"Default Rich Editor","title":"RichEditor","importPath":"./src/lib/components/ui/objects/RichEditor.stories.tsx","tags":["story"]},"sidepanel--default":{"type":"story","id":"sidepanel--default","name":"Default","title":"SidePanel","importPath":"./src/lib/components/ui/objects/SidePanel.stories.tsx","tags":["story"]},"sidepanel--without-expand":{"type":"story","id":"sidepanel--without-expand","name":"Without Expand","title":"SidePanel","importPath":"./src/lib/components/ui/objects/SidePanel.stories.tsx","tags":["story"]},"uilist--vertical-list":{"type":"story","id":"uilist--vertical-list","name":"Vertical List","title":"UiList","importPath":"./src/lib/components/ui/objects/UiList.stories.tsx","tags":["story"]},"uilist--horizontal-list":{"type":"story","id":"uilist--horizontal-list","name":"Horizontal List","title":"UiList","importPath":"./src/lib/components/ui/objects/UiList.stories.tsx","tags":["story"]}}}
